DefiTools
